georgio-2024.247.861.dist-info/METADATA
georgio-2024.247.861.dist-info/WHEEL
georgio-2024.247.861.dist-info/licenses/LICENSE
georgio-2024.247.861.dist-info/licenses/NOTICE
georgio/__init__.py
georgio/georgio.cpython-312-x86_64-linux-gnu.so
georgio-2024.247.861.dist-info/RECORD
