Metadata-Version: 2.3
Name: georgio
Version: 2024.247.861
Classifier: Programming Language :: Rust
Classifier: Programming Language :: Python :: Implementation :: CPython
Classifier: Programming Language :: Python :: Implementation :: PyPy
License-File: LICENSE
License-File: NOTICE
Summary: Fast Geo Rust functions for Python
Author-email: Spectric Labs <foss@spectric.com>
License: Apache-2.0
Requires-Python: >=3.7
Project-URL: repository, https://github.com/spectriclabs/georgio
